psylab/__init__.py
psylab/config.py
psylab/data.py
psylab/folder.py
psylab/grades.py
psylab/measurement.py
psylab/mtime.py
psylab/music.py
psylab/path.py
psylab/plot.py
psylab/stimulus_manager.py
psylab/string.py
psylab/subject.py
psylab/subject_manager.py
psylab/time.py
psylab/version.py
psylab/signal/__init__.py
psylab/signal/atten.py
psylab/signal/binaural.py
psylab/signal/compensate.py
psylab/signal/compression.py
psylab/signal/envelope.py
psylab/signal/f0.py
psylab/signal/filter.py
psylab/signal/freq_compression.py
psylab/signal/frequency.py
psylab/signal/interp.py
psylab/signal/level.py
psylab/signal/mix.py
psylab/signal/noise.py
psylab/signal/peakpick.py
psylab/signal/pitch.py
psylab/signal/ramps.py
psylab/signal/rir.py
psylab/signal/rms.py
psylab/signal/samp.py
psylab/signal/smooth.py
psylab/signal/soundfile.py
psylab/signal/spatial.py
psylab/signal/spec.py
psylab/signal/t60.py
psylab/signal/vocoder.py
psylab/signal/window.py
psylab/signal/zeropad.py
psylab/signal/ir/__init__.py
psylab/signal/ir/ir.py
psylab/stats/__init__.py
psylab/stats/anova.py
psylab/stats/cumr2.py
psylab/stats/pairwise.py
psylab/stats/rau.py
psylab/stats/rms_error.py
psylab/stats/dataview/__init__.py
psylab/stats/dataview/dataview.py
psylab-1.0.7.dist-info/AUTHORS.md
psylab-1.0.7.dist-info/COPYING
psylab-1.0.7.dist-info/METADATA
psylab-1.0.7.dist-info/WHEEL
psylab-1.0.7.dist-info/top_level.txt
psylab-1.0.7.dist-info/RECORD
