Metadata-Version: 2.1
Name: psylab
Version: 1.0.7
Summary: PsyLab: Psychophysics Lab
Home-page: http://www.github.com/cbrown1/psylab
Author: Christopher Brown
Author-email: cbrown1@pitt.edu
Maintainer: Christopher Brown
Maintainer-email: cbrown1@pitt.edu
Platform: any
Classifier: License :: OSI Approved :: GNU General Public License v3 or later (GPLv3+)
Classifier: Natural Language :: English
Classifier: Operating System :: OS Independent
Classifier: Operating System :: POSIX
Classifier: Operating System :: Unix
Classifier: Operating System :: Microsoft :: Windows
Classifier: Operating System :: MacOS
Classifier: Programming Language :: Python
Classifier: Programming Language :: Python :: 2.7
Classifier: Programming Language :: Python :: 3.5
Classifier: Programming Language :: Python :: 3.6
Classifier: Programming Language :: Python :: 3.7
Classifier: Environment :: Console
Classifier: Development Status :: 5 - Production/Stable
Classifier: Intended Audience :: Developers
Classifier: Intended Audience :: Science/Research
Classifier: Topic :: Multimedia :: Sound/Audio :: Speech
Classifier: Topic :: Multimedia :: Sound/Audio :: Analysis
Classifier: Topic :: Scientific/Engineering
License-File: COPYING
License-File: AUTHORS.md
Requires-Dist: numpy (>=1.2)
Requires-Dist: scipy (>=0.12)
Requires-Dist: matplotlib (>=1.2)
Requires-Dist: pyaml
Requires-Dist: yamlreader
Requires-Dist: daiquiri
